unifmu/__init__.py
unifmu/authoring.py
unifmu/cli.py
unifmu/fmi2.py
unifmu/generate.py
unifmu/gui.py
unifmu/resources/backends.toml
unifmu/resources/backends/csharp/.gitignore
unifmu/resources/backends/csharp/CommandService.cs
unifmu/resources/backends/csharp/adder.cs
unifmu/resources/backends/csharp/csharp.csproj
unifmu/resources/backends/csharp/fmi2.cs
unifmu/resources/backends/csharp/launch.cs
unifmu/resources/backends/csharp/launch.toml
unifmu/resources/backends/csharp/schemas/UnifmuFmi2.cs
unifmu/resources/backends/csharp/schemas/UnifmuFmi2Grpc.cs
unifmu/resources/backends/csharp/schemas/unifmu_fmi2.proto
unifmu/resources/backends/docker/Dockerfile_python
unifmu/resources/backends/docker/README.md
unifmu/resources/backends/docker/bootstrap.py
unifmu/resources/backends/docker/deploy.ps1
unifmu/resources/backends/docker/deploy.sh
unifmu/resources/backends/docker/launch.toml
unifmu/resources/backends/empty/launch.toml
unifmu/resources/backends/java/.gitignore
unifmu/resources/backends/java/build.ps1
unifmu/resources/backends/java/build.sh
unifmu/resources/backends/java/launch.toml
unifmu/resources/backends/java/pom.xml
unifmu/resources/backends/java/src/main/java/fmi2_proto/Fmi2Proto.java
unifmu/resources/backends/java/src/main/java/fmu/Adder.java
unifmu/resources/backends/java/src/main/java/fmu/Fmi2.java
unifmu/resources/backends/java/src/main/java/fmu/Launch.java
unifmu/resources/backends/java/src/test/java/fmu/AppTest.java
unifmu/resources/backends/matlab/README.md
unifmu/resources/backends/matlab/launch.toml
unifmu/resources/backends/matlab/matlab_interface.py
unifmu/resources/backends/matlab/matlab_proxy.py
unifmu/resources/backends/matlab/requirements.txt
unifmu/resources/backends/matlab/matlabcode/cancel_step.m
unifmu/resources/backends/matlab/matlabcode/deserialize.m
unifmu/resources/backends/matlab/matlabcode/do_step.m
unifmu/resources/backends/matlab/matlabcode/enter_initialization_mode.m
unifmu-0.0.3.dist-info/METADATA
unifmu-0.0.3.dist-info/WHEEL
unifmu-0.0.3.dist-info/entry_points.txt
unifmu-0.0.3.dist-info/top_level.txt
unifmu-0.0.3.dist-info/RECORD
